jupyfmt/__init__.py
jupyfmt/main.py
jupyfmt-0.5.3.dist-info/entry_points.txt
jupyfmt-0.5.3.dist-info/LICENSE
jupyfmt-0.5.3.dist-info/WHEEL
jupyfmt-0.5.3.dist-info/METADATA
jupyfmt-0.5.3.dist-info/RECORD
