Metadata-Version: 2.1
Name: jupyfmt
Version: 0.5.3
Summary: Format code in Jupyter notebooks
Home-page: https://github.com/kpj/jupyfmt
License: MIT
Author: kpj
Author-email: kim.philipp.jablonski@gmail.com
Requires-Python: >=3.8.0,<4.0.0
Classifier: License :: OSI Approved :: MIT License
Classifier: Programming Language :: Python :: 3
Classifier: Programming Language :: Python :: 3.8
Classifier: Programming Language :: Python :: 3.9
Requires-Dist: black (>=21.4,<23.0)
Requires-Dist: click (>=7.1.2,<9.0.0)
Requires-Dist: nbformat (>=5.1.2,<6.0.0)
Project-URL: Repository, https://github.com/kpj/jupyfmt
